{
  "schemaVersion": "UBCv0.1",
  "course": "ARTC 411",
  "originalPrerequisite": "One of ARTC 310, ARTC 311.",
  "originalCorequisite": null,
  "status": "parsed",
  "lastUpdated": "2025-07-04T12:23:58.480Z",
  "parsedRequirements": {
    "department": "ARTC",
    "code": "411",
    "prerequisites": {
      "type": "group",
      "logic": "ONE_OF",
      "children": [
        {
          "type": "course",
          "course": "ARTC 310"
        },
        {
          "type": "course",
          "course": "ARTC 311"
        }
      ]
    }
  }
}