{
  "schemaVersion": "UBCv0.1",
  "course": "ASTR 200",
  "originalPrerequisite": "Either (a) one of PHYS 101, PHYS 106, PHYS 107, PHYS 117, PHYS 131, PHYS 157, PHYS 153 and one of MATH 101, MATH 103, MATH 105, MATH 121; or (b) SCIE 001.",
  "originalCorequisite": null,
  "status": "parsed",
  "lastUpdated": "2025-07-04T12:25:14.900Z",
  "parsedRequirements": {
    "department": "ASTR",
    "code": "200",
    "prerequisites": {
      "type": "group",
      "logic": "ONE_OF",
      "children": [
        {
          "type": "group",
          "logic": "ALL_OF",
          "children": [
            {
              "type": "group",
              "logic": "ONE_OF",
              "children": [
                {
                  "type": "course",
                  "course": "PHYS 101"
                },
                {
                  "type": "course",
                  "course": "PHYS 106"
                },
                {
                  "type": "course",
                  "course": "PHYS 107"
                },
                {
                  "type": "course",
                  "course": "PHYS 117"
                },
                {
                  "type": "course",
                  "course": "PHYS 131"
                },
                {
                  "type": "course",
                  "course": "PHYS 157"
                },
                {
                  "type": "course",
                  "course": "PHYS 153"
                }
              ]
            },
            {
              "type": "group",
              "logic": "ONE_OF",
              "children": [
                {
                  "type": "course",
                  "course": "MATH 101"
                },
                {
                  "type": "course",
                  "course": "MATH 103"
                },
                {
                  "type": "course",
                  "course": "MATH 105"
                },
                {
                  "type": "course",
                  "course": "MATH 121"
                }
              ]
            }
          ]
        },
        {
          "type": "course",
          "course": "SCIE 001"
        }
      ]
    }
  }
}