{
  "schemaVersion": "UBCv0.1",
  "course": "BMEG 470",
  "originalPrerequisite": "All of BMEG 245, BMEG 250, BMEG 350.",
  "originalCorequisite": null,
  "status": "parsed",
  "lastUpdated": "2025-07-04T12:33:12.221Z",
  "parsedRequirements": {
    "department": "BMEG",
    "code": "470",
    "prerequisites": {
      "type": "group",
      "logic": "ALL_OF",
      "children": [
        {
          "type": "course",
          "course": "BMEG 245"
        },
        {
          "type": "course",
          "course": "BMEG 250"
        },
        {
          "type": "course",
          "course": "BMEG 350"
        }
      ]
    }
  }
}