{
  "schemaVersion": "UBCv0.1",
  "course": "PHYS 350",
  "originalPrerequisite": "One of ENPH 270, PHYS 270.",
  "originalCorequisite": null,
  "status": "parsed",
  "lastUpdated": "2025-07-04T23:04:10.741Z",
  "parsedRequirements": {
    "department": "PHYS",
    "code": "350",
    "prerequisites": {
      "type": "group",
      "logic": "ONE_OF",
      "children": [
        {
          "type": "course",
          "course": "ENPH 270"
        },
        {
          "type": "course",
          "course": "PHYS 270"
        }
      ]
    }
  }
}